Source/message_scheduler.sv
`timescale 1ns / 10ps
/* verilator lint_off ASCRANGE */
module message_scheduler (
    input  logic clk,
    input  logic n_rst,
    input  logic load,
    input  logic [0:15][31:0] data_in,
    output logic [31:0] data_out
);

logic [0:15][31:0] buffer, next_buffer;
logic [3:0] ptr, next_ptr;
logic [31:0] s0, s1, next_data_out;

always_ff @(posedge clk or negedge n_rst) begin
    if (!n_rst) begin
        buffer <= 0;
        ptr <= 4'b0;
        data_out <= 32'b0;
    end else begin
        buffer <= next_buffer;
        ptr <= next_ptr;
        data_out <= next_data_out;
    end
end

always_comb begin
    next_buffer = buffer;
    next_ptr = ptr;
    next_data_out = data_out;

    // Calculate s0 and s1 based on previous saved message words
    s0 = {buffer[(ptr + 1)  % 16][6:0] , buffer[(ptr + 1)  % 16][31:7] } ^
         {buffer[(ptr + 1)  % 16][17:0], buffer[(ptr + 1)  % 16][31:18]} ^
         (buffer[(ptr + 1)  % 16] >> 3);

    s1 = {buffer[(ptr + 14) % 16][16:0], buffer[(ptr + 14) % 16][31:17]} ^
         {buffer[(ptr + 14) % 16][18:0], buffer[(ptr + 14) % 16][31:19]} ^
         (buffer[(ptr + 14) % 16] >> 10);


    // Reset buffer and ptr on load, otherwise update buffer and ptr to calculate next message word
    if (load) begin
        next_buffer = data_in;
        next_ptr = 4'b0;
        next_data_out = data_in[0];
    end else begin
        next_buffer[ptr] = buffer[ptr] + s0 + buffer[(ptr + 9) % 16] + s1;
        next_data_out = buffer[(ptr+1) % 16];
        next_ptr = (ptr == 4'd15)? 4'b0 : ptr + 1'b1;
    end
end
/* verilator lint_on ASCRANGE */
endmodule

Testbench/tb_message_scheduler.sv
`timescale 1ns / 10ps
/* verilator coverage_off */
/* verilator lint_off ASCRANGE */
module tb_message_scheduler ();

    localparam CLK_PERIOD = 10ns;

    /* verilator lint_off UNUSEDSIGNAL */
    logic clk, n_rst, load;
    logic [0:15][31:0] data_in;
    logic [0:63][31:0] expected_data_out;
    logic [31:0] data_out;
    logic [31:0] expected_word_out;
    logic tb_check_pulse;
    /* verilator lint_on UNUSEDSIGNAL */

    message_scheduler dut (
        .clk(clk),
        .n_rst(n_rst),
        .load(load),
        .data_in(data_in),
        .data_out(data_out)
    );

    // always @(posedge clk)
    // $display("T=%0t | load=%b | data_out=%h", $time, load, data_out);

    always begin
        clk = 0;
        #(CLK_PERIOD / 2.0);
        clk = 1;
        #(CLK_PERIOD / 2.0);
    end

    task reset_dut;
    begin
        n_rst = 0;
        @(posedge clk);
        @(posedge clk); 
        n_rst = 1;
        @(negedge clk);
    end
    endtask

    task compute_message_words;
        input  [0:15][31:0] msg_block;
        output [0:63][31:0] w;
    begin
        logic [31:0] s0, s1;
        integer i;

        for (i = 0; i < 16; i = i + 1) begin
            w[i] = msg_block[i];
        end

        for (i = 16; i < 64; i = i + 1) begin
            s0 = {w[i-15][6:0], w[i-15][31:7]} ^ {w[i-15][17:0], w[i-15][31:18]} ^ (w[i-15] >> 3);
            s1 = {w[i-2][16:0], w[i-2][31:17]} ^ {w[i-2][18:0], w[i-2][31:19]} ^ (w[i-2] >> 10);
            w[i] = w[i-16] + s0 + w[i-7] + s1;
        end

    end
    endtask

    task check_word;
        input [31:0] expected_word;
        input [31:0] actual_word;
        input integer index;
    begin
        /* verilator lint_off UNUSEDSIGNAL */
        logic mismatch;
        /* verilator lint_on UNUSEDSIGNAL */
        
        mismatch = (expected_word !== actual_word);
        if (mismatch) begin
            $display("Index : %d . Word mismatch. Expected: %h, Got: %h", index, expected_word, actual_word);
        end else begin
            $display("Index : %d . Word match: %h", index, actual_word);
        end
    end
    endtask


    initial begin
        reset_dut; // Resets DUT, ends at a negedge
        expected_word_out = 32'b0;

        // Test 1 abc
        data_in = '{
            32'h61626380, 32'h00000000, 32'h00000000, 32'h00000000,
            32'h00000000, 32'h00000000, 32'h00000000, 32'h00000000,
            32'h00000000, 32'h00000000, 32'h00000000, 32'h00000000,
            32'h00000000, 32'h00000000, 32'h00000000, 32'h00000018
        };
        
        compute_message_words(data_in, expected_data_out);
        
        // At negedge, set up inputs for the *next* posedge
        load = 1;
        @(negedge clk);

        // At this negedge, de-assert load for the *next* cycle
        load = 0;
        
        // Loop 64 times
        for (int i = 0; i < 64; i++) begin
            @(posedge clk); 
            tb_check_pulse = 1'b1;
            expected_word_out = expected_data_out[i];
            check_word(expected_word_out, data_out, i);
            @(negedge clk);
            tb_check_pulse = 1'b0; 
        end

        $finish;
    end



    initial begin
        void'($system("mkdir -p waves"));
        $dumpfile("waves/tb_message_scheduler.vcd");
        $dumpvars(0, tb_message_scheduler);
    end
    
endmodule
/* verilator lint_on ASCRANGE */
/* verilator coverage_on */

waves/tb_message_scheduler.vcd
$version Generated by VerilatedVcd $end
$timescale 10ps $end
 $scope module tb_message_scheduler $end
  $var real 64 E! CLK_PERIOD $end
  $var wire 1 B! clk $end
  $var wire 1 # n_rst $end
  $var wire 1 $ load $end
  $var wire 512 % data_in [511:0] $end
  $var wire 2048 5 expected_data_out [2047:0] $end
  $var wire 32 0! data_out [31:0] $end
  $var wire 32 u expected_word_out [31:0] $end
  $var wire 1 v tb_check_pulse $end
  $scope module check_word__Vstatic__unnamedblk2 $end
   $var wire 1 w mismatch $end
  $upscope $end
  $scope module compute_message_words__Vstatic__unnamedblk1 $end
   $var wire 32 x s0 [31:0] $end
   $var wire 32 y s1 [31:0] $end
   $var wire 32 z i [31:0] $end
  $upscope $end
  $scope module dut $end
   $var wire 1 B! clk $end
   $var wire 1 # n_rst $end
   $var wire 1 $ load $end
   $var wire 512 % data_in [511:0] $end
   $var wire 32 0! data_out [31:0] $end
   $var wire 512 1! buffer [511:0] $end
   $var wire 512 | next_buffer [511:0] $end
   $var wire 4 A! ptr [3:0] $end
   $var wire 4 C! next_ptr [3:0] $end
   $var wire 32 .! s0 [31:0] $end
   $var wire 32 /! s1 [31:0] $end
   $var wire 32 D! next_data_out [31:0] $end
  $upscope $end
  $scope module unnamedblk3 $end
   $var wire 32 { i [31:0] $end
  $upscope $end
 $upscope $end
$enddefinitions $end


#0
0#
0$
b00000000000000000000000000000000000000000000000000000000000000000000000000000000000000000000000000000000000000000000000000000000000000000000000000000000000000000000000000000000000000000000000000000000000000000000000000000000000000000000000000000000000000000000000000000000000000000000000000000000000000000000000000000000000000000000000000000000000000000000000000000000000000000000000000000000000000000000000000000000000000000000000000000000000000000000000000000000000000000000000000000000000000000000000000000000 %
b00000000000000000000000000000000000000000000000000000000000000000000000000000000000000000000000000000000000000000000000000000000000000000000000000000000000000000000000000000000000000000000000000000000000000000000000000000000000000000000000000000000000000000000000000000000000000000000000000000000000000000000000000000000000000000000000000000000000000000000000000000000000000000000000000000000000000000000000000000000000000000000000000000000000000000000000000000000000000000000000000000000000000000000000000000000000000000000000000000000000000000000000000000000000000000000000000000000000000000000000000000000000000000000000000000000000000000000000000000000000000000000000000000000000000000000000000000000000000000000000000000000000000000000000000000000000000000000000000000000000000000000000000000000000000000000000000000000000000000000000000000000000000000000000000000000000000000000000000000000000000000000000000000000000000000000000000000000000000000000000000000000000000000000000000000000000000000000000000000000000000000000000000000000000000000000000000000000000000000000000000000000000000000000000000000000000000000000000000000000000000000000000000000000000000000000000000000000000000000000000000000000000000000000000000000000000000000000000000000000000000000000000000000000000000000000000000000000000000000000000000000000000000000000000000000000000000000000000000000000000000000000000000000000000000000000000000000000000000000000000000000000000000000000000000000000000000000000000000000000000000000000000000000000000000000000000000000000000000000000000000000000000000000000000000000000000000000000000000000000000000000000000000000000000000000000000000000000000000000000000000000000000000000000000000000000000000000000000000000000000000000000000000000000000000000000000000000000000000000000000000000000000000000000000000000000000000000000000000000000000000000000000000000000000000000000000000000000000000000000000000000000000000000000000000000000000000000000000000000000000000000000000000000000000000000000000000000000000000000000000000000000 5
b00000000000000000000000000000000 u
0v
0w
b00000000000000000000000000000000 x
b00000000000000000000000000000000 y
b00000000000000000000000000000000 z
b00000000000000000000000000000000 {
b00000000000000000000000000000000000000000000000000000000000000000000000000000000000000000000000000000000000000000000000000000000000000000000000000000000000000000000000000000000000000000000000000000000000000000000000000000000000000000000000000000000000000000000000000000000000000000000000000000000000000000000000000000000000000000000000000000000000000000000000000000000000000000000000000000000000000000000000000000000000000000000000000000000000000000000000000000000000000000000000000000000000000000000000000000000 |
b00000000000000000000000000000000 .!
b00000000000000000000000000000000 /!
b00000000000000000000000000000000 0!
b00000000000000000000000000000000000000000000000000000000000000000000000000000000000000000000000000000000000000000000000000000000000000000000000000000000000000000000000000000000000000000000000000000000000000000000000000000000000000000000000000000000000000000000000000000000000000000000000000000000000000000000000000000000000000000000000000000000000000000000000000000000000000000000000000000000000000000000000000000000000000000000000000000000000000000000000000000000000000000000000000000000000000000000000000000000 1!
b0000 A!
0B!
b0001 C!
b00000000000000000000000000000000 D!
r10 E!
#500
1B!
#1000
0B!
#1500
1#
b0001 A!
1B!
b0010 C!
#2000
1$
b01100001011000100110001110000000000000000000000000000000000000000000000000000000000000000000000000000000000000000000000000000000000000000000000000000000000000000000000000000000000000000000000000000000000000000000000000000000000000000000000000000000000000000000000000000000000000000000000000000000000000000000000000000000000000000000000000000000000000000000000000000000000000000000000000000000000000000000000000000000000000000000000000000000000000000000000000000000000000000000000000000000000000000000000000011000 %
b01100001011000100110001110000000000000000000000000000000000000000000000000000000000000000000000000000000000000000000000000000000000000000000000000000000000000000000000000000000000000000000000000000000000000000000000000000000000000000000000000000000000000000000000000000000000000000000000000000000000000000000000000000000000000000000000000000000000000000000000000000000000000000000000000000000000000000000000000000000000000000000000000000000000000000000000000000000000000000000000000000000000000000000000000011000011000010110001001100011100000000000000000001111000000000000000001111101101010000110010000000101011000000000000000000011110001100011111010011101011110110111100000000001100000111111110000000000000100101101110010111111110110111110001011100010110000111000111011001000001000010101110000011010101101110011011001111001101000101110010110111100001110010000100100110010011001100011110001011011100111010010000010011101011001111110110010000111001001101100101101110000001000010011100010100100110100111011011110010111001110111001001111110101100110010111111100111011011010001011101001110011101011111111010011111111110000011111000100001010010111000110001000001010100010110011100110010110011100101010111110000011000010101001010000001001111000110011111000100100011001000001010100100010100111110100011110111111100101001111000010100110010011110101101000111110001001000110101001111001001001110011001100111011101000110000110001000111011000111111001010000100000010101011111100100111011110100010100100001101010111010000011001011100010000111101101011111011001111101000100111001011110011000111011000010111110110111011100111100110011011000011010010101001100110010011011001100111100001001011101011011110110111011100001000010100011000101011110000010100100001110100011100101100101100100000111101111010100110011110111101010111101110011100110111101011111001101011001000111000100111111110001100001001010111100111100010111100100011010100101110100100001111111100111100010101011001101000101100101111111110001110111010101011101000101100110000010010101100011110110111101011 5
b00101010111000110101001011100101 x
b11110010000110101001110101011111 y
b00000000000000000000000001000000 z
b01100001011000100110001110000000000000000000000000000000000000000000000000000000000000000000000000000000000000000000000000000000000000000000000000000000000000000000000000000000000000000000000000000000000000000000000000000000000000000000000000000000000000000000000000000000000000000000000000000000000000000000000000000000000000000000000000000000000000000000000000000000000000000000000000000000000000000000000000000000000000000000000000000000000000000000000000000000000000000000000000000000000000000000000000011000 |
0B!
b0000 C!
b01100001011000100110001110000000 D!
#2500
b01100001011000100110001110000000 0!
b01100001011000100110001110000000000000000000000000000000000000000000000000000000000000000000000000000000000000000000000000000000000000000000000000000000000000000000000000000000000000000000000000000000000000000000000000000000000000000000000000000000000000000000000000000000000000000000000000000000000000000000000000000000000000000000000000000000000000000000000000000000000000000000000000000000000000000000000000000000000000000000000000000000000000000000000000000000000000000000000000000000000000000000000000011000 1!
b0000 A!
1B!
#3000
0$
b01100001011000100110001110000000 u
0B!
b0001 C!
b00000000000000000000000000000000 D!
#3500
1v
b01100001011000100110001110000000000000000000111100000000000000000000000000000000000000000000000000000000000000000000000000000000000000000000000000000000000000000000000000000000000000000000000000000000000000000000000000000000000000000000000000000000000000000000000000000000000000000000000000000000000000000000000000000000000000000000000000000000000000000000000000000000000000000000000000000000000000000000000000000000000000000000000000000000000000000000000000000000000000000000000000000000000000000000000000011000 |
b00000000000011110000000000000000 /!
b00000000000000000000000000000000 0!
b0001 A!
1B!
b0010 C!
#4000
b00000000000000000000000000000000 u
0v
b00000000000000000000000000000001 {
0B!
#4500
1v
b01100001011000100110001110000000000000000000111100000000000000000111110110101000011001000000010100000000000000000000000000000000000000000000000000000000000000000000000000000000000000000000000000000000000000000000000000000000000000000000000000000000000000000000000000000000000000000000000000000000000000000000000000000000000000000000000000000000000000000000000000000000000000000000000000000000000000000000000000000000000000000000000000000000000000000000000000000000000000000000000000000000000000000000000000011000 |
b01111101101010000110010000000101 /!
b01100001011000100110001110000000000000000000111100000000000000000000000000000000000000000000000000000000000000000000000000000000000000000000000000000000000000000000000000000000000000000000000000000000000000000000000000000000000000000000000000000000000000000000000000000000000000000000000000000000000000000000000000000000000000000000000000000000000000000000000000000000000000000000000000000000000000000000000000000000000000000000000000000000000000000000000000000000000000000000000000000000000000000000000000011000 1!
b0010 A!
1B!
b0011 C!
#5000
0v
b00000000000000000000000000000010 {
0B!
#5500
1v
b01100001011000100110001110000000000000000000111100000000000000000111110110101000011001000000010101100000000000000000001111000110000000000000000000000000000000000000000000000000000000000000000000000000000000000000000000000000000000000000000000000000000000000000000000000000000000000000000000000000000000000000000000000000000000000000000000000000000000000000000000000000000000000000000000000000000000000000000000000000000000000000000000000000000000000000000000000000000000000000000000000000000000000000000000011000 |
b01100000000000000000001111000110 /!
b01100001011000100110001110000000000000000000111100000000000000000111110110101000011001000000010100000000000000000000000000000000000000000000000000000000000000000000000000000000000000000000000000000000000000000000000000000000000000000000000000000000000000000000000000000000000000000000000000000000000000000000000000000000000000000000000000000000000000000000000000000000000000000000000000000000000000000000000000000000000000000000000000000000000000000000000000000000000000000000000000000000000000000000000000011000 1!
b0011 A!
1B!
b0100 C!
#6000
0v
b00000000000000000000000000000011 {
0B!
#6500
1v
b01100001011000100110001110000000000000000000111100000000000000000111110110101000011001000000010101100000000000000000001111000110001111101001110101111011011110000000000000000000000000000000000000000000000000000000000000000000000000000000000000000000000000000000000000000000000000000000000000000000000000000000000000000000000000000000000000000000000000000000000000000000000000000000000000000000000000000000000000000000000000000000000000000000000000000000000000000000000000000000000000000000000000000000000000011000 |
b00111110100111010111101101111000 /!
b01100001011000100110001110000000000000000000111100000000000000000111110110101000011001000000010101100000000000000000001111000110000000000000000000000000000000000000000000000000000000000000000000000000000000000000000000000000000000000000000000000000000000000000000000000000000000000000000000000000000000000000000000000000000000000000000000000000000000000000000000000000000000000000000000000000000000000000000000000000000000000000000000000000000000000000000000000000000000000000000000000000000000000000000000011000 1!
b0100 A!
1B!
b0101 C!
#7000
0v
b00000000000000000000000000000100 {
0B!
#7500
1v
b01100001011000100110001110000000000000000000111100000000000000000111110110101000011001000000010101100000000000000000001111000110001111101001110101111011011110000000000110000011111111000000000000000000000000000000000000000000000000000000000000000000000000000000000000000000000000000000000000000000000000000000000000000000000000000000000000000000000000000000000000000000000000000000000000000000000000000000000000000000000000000000000000000000000000000000000000000000000000000000000000000000000000000000000000011000 |
b00000001100000111111110000000000 /!
b01100001011000100110001110000000000000000000111100000000000000000111110110101000011001000000010101100000000000000000001111000110001111101001110101111011011110000000000000000000000000000000000000000000000000000000000000000000000000000000000000000000000000000000000000000000000000000000000000000000000000000000000000000000000000000000000000000000000000000000000000000000000000000000000000000000000000000000000000000000000000000000000000000000000000000000000000000000000000000000000000000000000000000000000000011000 1!
b0101 A!
1B!
b0110 C!
#8000
0v
b00000000000000000000000000000101 {
0B!
#8500
1v
b01100001011000100110001110000000000000000000111100000000000000000111110110101000011001000000010101100000000000000000001111000110001111101001110101111011011110000000000110000011111111000000000000010010110111001011111111011011000000000000000000000000000000000000000000000000000000000000000000000000000000000000000000000000000000000000000000000000000000000000000000000000000000000000000000000000000000000000000000000000000000000000000000000000000000000000000000000000000000000000000000000000000000000000000000011000 |
b00010010110111001011111111000011 /!
b01100001011000100110001110000000000000000000111100000000000000000111110110101000011001000000010101100000000000000000001111000110001111101001110101111011011110000000000110000011111111000000000000000000000000000000000000000000000000000000000000000000000000000000000000000000000000000000000000000000000000000000000000000000000000000000000000000000000000000000000000000000000000000000000000000000000000000000000000000000000000000000000000000000000000000000000000000000000000000000000000000000000000000000000000011000 1!
b0110 A!
1B!
b0111 C!
#9000
0v
b00000000000000000000000000000110 {
0B!
#9500
1v
b01100001011000100110001110000000000000000000111100000000000000000111110110101000011001000000010101100000000000000000001111000110001111101001110101111011011110000000000110000011111111000000000000010010110111001011111111011011111000101110001011000011100011100000000000000000000000000000000000000000000000000000000000000000000000000000000000000000000000000000000000000000000000000000000000000000000000000000000000000000000000000000000000000000000000000000000000000000000000000000000000000000000000000000000000011000 |
b10000001100000000110000000001110 /!
b01100001011000100110001110000000000000000000111100000000000000000111110110101000011001000000010101100000000000000000001111000110001111101001110101111011011110000000000110000011111111000000000000010010110111001011111111011011000000000000000000000000000000000000000000000000000000000000000000000000000000000000000000000000000000000000000000000000000000000000000000000000000000000000000000000000000000000000000000000000000000000000000000000000000000000000000000000000000000000000000000000000000000000000000000011000 1!
b0111 A!
1B!
b1000 C!
#10000
0v
b00000000000000000000000000000111 {
0B!
#10500
1v
b01100001011000100110001110000000000000000000111100000000000000000111110110101000011001000000010101100000000000000000001111000110001111101001110101111011011110000000000110000011111111000000000000010010110111001011111111011011111000101110001011000011100011101100100000100001010111000001101000000000000000000000000000000000000000000000000000000000000000000000000000000000000000000000000000000000000000000000000000000000000000000000000000000000000000000000000000000000000000000000000000000000000000000000000000011000 |
b11001000000100100101110000011010 /!
b01100001011000100110001110000000000000000000111100000000000000000111110110101000011001000000010101100000000000000000001111000110001111101001110101111011011110000000000110000011111111000000000000010010110111001011111111011011111000101110001011000011100011100000000000000000000000000000000000000000000000000000000000000000000000000000000000000000000000000000000000000000000000000000000000000000000000000000000000000000000000000000000000000000000000000000000000000000000000000000000000000000000000000000000000011000 1!
b1000 A!
1B!
b1001 C!
#11000
0v
b00000000000000000000000000001000 {
0B!
#11500
1v
b01100001011000100110001110000000000000000000111100000000000000000111110110101000011001000000010101100000000000000000001111000110001111101001110101111011011110000000000110000011111111000000000000010010110111001011111111011011111000101110001011000011100011101100100000100001010111000001101010110111001101100111100110100010000000000000000000000000000000000000000000000000000000000000000000000000000000000000000000000000000000000000000000000000000000000000000000000000000000000000000000000000000000000000000000011000 |
b00111001100011100001010110011101 /!
b01100001011000100110001110000000000000000000111100000000000000000111110110101000011001000000010101100000000000000000001111000110001111101001110101111011011110000000000110000011111111000000000000010010110111001011111111011011111000101110001011000011100011101100100000100001010111000001101000000000000000000000000000000000000000000000000000000000000000000000000000000000000000000000000000000000000000000000000000000000000000000000000000000000000000000000000000000000000000000000000000000000000000000000000000011000 1!
b1001 A!
1B!
b1010 C!
#12000
0v
b00000000000000000000000000001001 {
0B!
#12500
1v
b01100001011000100110001110000000000000000000111100000000000000000111110110101000011001000000010101100000000000000000001111000110001111101001110101111011011110000000000110000011111111000000000000010010110111001011111111011011111000101110001011000011100011101100100000100001010111000001101010110111001101100111100110100010111001011011110000111001000010010000000000000000000000000000000000000000000000000000000000000000000000000000000000000000000000000000000000000000000000000000000000000000000000000000000000011000 |
b10000101101111000011010101000011 /!
b01100001011000100110001110000000000000000000111100000000000000000111110110101000011001000000010101100000000000000000001111000110001111101001110101111011011110000000000110000011111111000000000000010010110111001011111111011011111000101110001011000011100011101100100000100001010111000001101010110111001101100111100110100010000000000000000000000000000000000000000000000000000000000000000000000000000000000000000000000000000000000000000000000000000000000000000000000000000000000000000000000000000000000000000000011000 1!
b1010 A!
1B!
b1011 C!
#13000
0v
b00000000000000000000000000001010 {
0B!
#13500
1v
b01100001011000100110001110000000000000000000111100000000000000000111110110101000011001000000010101100000000000000000001111000110001111101001110101111011011110000000000110000011111111000000000000010010110111001011111111011011111000101110001011000011100011101100100000100001010111000001101010110111001101100111100110100010111001011011110000111001000010010011001001100110001111000101101100000000000000000000000000000000000000000000000000000000000000000000000000000000000000000000000000000000000000000000000000011000 |
b11110011110010001100000011100011 /!
b01100001011000100110001110000000000000000000111100000000000000000111110110101000011001000000010101100000000000000000001111000110001111101001110101111011011110000000000110000011111111000000000000010010110111001011111111011011111000101110001011000011100011101100100000100001010111000001101010110111001101100111100110100010111001011011110000111001000010010000000000000000000000000000000000000000000000000000000000000000000000000000000000000000000000000000000000000000000000000000000000000000000000000000000000011000 1!
b1011 A!
1B!
b1100 C!
#14000
0v
b00000000000000000000000000001011 {
0B!
#14500
1v
b01100001011000100110001110000000000000000000111100000000000000000111110110101000011001000000010101100000000000000000001111000110001111101001110101111011011110000000000110000011111111000000000000010010110111001011111111011011111000101110001011000011100011101100100000100001010111000001101010110111001101100111100110100010111001011011110000111001000010010011001001100110001111000101101110011101001000001001110101100111000000000000000000000000000000000000000000000000000000000000000000000000000000000000000000011000 |
b10011011100111001010000101100111 /!
b01100001011000100110001110000000000000000000111100000000000000000111110110101000011001000000010101100000000000000000001111000110001111101001110101111011011110000000000110000011111111000000000000010010110111001011111111011011111000101110001011000011100011101100100000100001010111000001101010110111001101100111100110100010111001011011110000111001000010010011001001100110001111000101101100000000000000000000000000000000000000000000000000000000000000000000000000000000000000000000000000000000000000000000000000011000 1!
b1100 A!
1B!
b1101 C!
#15000
0v
b00000000000000000000000000001100 {
0B!
#15500
1v
b01100001011000100110001110000000000000000000111100000000000000000111110110101000011001000000010101100000000000000000001111000110001111101001110101111011011110000000000110000011111111000000000000010010110111001011111111011011111000101110001011000011100011101100100000100001010111000001101010110111001101100111100110100010111001011011110000111001000010010011001001100110001111000101101110011101001000001001110101100111111011001000011100100110110010110000000000000000000000000000000000000000000000000000000000011000 |
b11011001101010100110011011110000 /!
b01100001011000100110001110000000000000000000111100000000000000000111110110101000011001000000010101100000000000000000001111000110001111101001110101111011011110000000000110000011111111000000000000010010110111001011111111011011111000101110001011000011100011101100100000100001010111000001101010110111001101100111100110100010111001011011110000111001000010010011001001100110001111000101101110011101001000001001110101100111000000000000000000000000000000000000000000000000000000000000000000000000000000000000000000011000 1!
b1101 A!
1B!
b1110 C!
#16000
0v
b00000000000000000000000000001101 {
0B!
#16500
1v
b01100001011000100110001110000000000000000000111100000000000000000111110110101000011001000000010101100000000000000000001111000110001111101001110101111011011110000000000110000011111111000000000000010010110111001011111111011011111000101110001011000011100011101100100000100001010111000001101010110111001101100111100110100010111001011011110000111001000010010011001001100110001111000101101110011101001000001001110101100111111011001000011100100110110010110111000000100001001110001010010000000000000000000000000000011000 |
b00110000000001100000000000000011 .!
b01011101001110000111010100010011 /!
b01100001011000100110001110000000000000000000111100000000000000000111110110101000011001000000010101100000000000000000001111000110001111101001110101111011011110000000000110000011111111000000000000010010110111001011111111011011111000101110001011000011100011101100100000100001010111000001101010110111001101100111100110100010111001011011110000111001000010010011001001100110001111000101101110011101001000001001110101100111111011001000011100100110110010110000000000000000000000000000000000000000000000000000000000011000 1!
b1110 A!
1B!
b1111 C!
b00000000000000000000000000011000 D!
#17000
0v
b00000000000000000000000000001110 {
0B!
#17500
1v
b01100001011000100110001110000000000000000000111100000000000000000111110110101000011001000000010101100000000000000000001111000110001111101001110101111011011110000000000110000011111111000000000000010010110111001011111111011011111000101110001011000011100011101100100000100001010111000001101010110111001101100111100110100010111001011011110000111001000010010011001001100110001111000101101110011101001000001001110101100111111011001000011100100110110010110111000000100001001110001010010011010011101101111001011100111011 |
b10010100000011101001000011101111 .!
b01110111100001111010101000011010 /!
b00000000000000000000000000011000 0!
b01100001011000100110001110000000000000000000111100000000000000000111110110101000011001000000010101100000000000000000001111000110001111101001110101111011011110000000000110000011111111000000000000010010110111001011111111011011111000101110001011000011100011101100100000100001010111000001101010110111001101100111100110100010111001011011110000111001000010010011001001100110001111000101101110011101001000001001110101100111111011001000011100100110110010110111000000100001001110001010010000000000000000000000000000011000 1!
b1111 A!
1B!
b0000 C!
b01100001011000100110001110000000 D!
#18000
b00000000000000000000000000011000 u
0v
b00000000000000000000000000001111 {
0B!
#18500
1v
b10010011111101011001100101111111000000000000111100000000000000000111110110101000011001000000010101100000000000000000001111000110001111101001110101111011011110000000000110000011111111000000000000010010110111001011111111011011111000101110001011000011100011101100100000100001010111000001101010110111001101100111100110100010111001011011110000111001000010010011001001100110001111000101101110011101001000001001110101100111111011001000011100100110110010110111000000100001001110001010010011010011101101111001011100111011 |
b11000000000000011111111000000011 .!
b10111011010110101011111001011010 /!
b01100001011000100110001110000000 0!
b01100001011000100110001110000000000000000000111100000000000000000111110110101000011001000000010101100000000000000000001111000110001111101001110101111011011110000000000110000011111111000000000000010010110111001011111111011011111000101110001011000011100011101100100000100001010111000001101010110111001101100111100110100010111001011011110000111001000010010011001001100110001111000101101110011101001000001001110101100111111011001000011100100110110010110111000000100001001110001010010011010011101101111001011100111011 1!
b0000 A!
1B!
b0001 C!
b00000000000011110000000000000000 D!
#19000
b01100001011000100110001110000000 u
0v
b00000000000000000000000000010000 {
0B!
#19500
1v
b10010011111101011001100101111111001110110110100010111010011100110111110110101000011001000000010101100000000000000000001111000110001111101001110101111011011110000000000110000011111111000000000000010010110111001011111111011011111000101110001011000011100011101100100000100001010111000001101010110111001101100111100110100010111001011011110000111001000010010011001001100110001111000101101110011101001000001001110101100111111011001000011100100110110010110111000000100001001110001010010011010011101101111001011100111011 |
b00011100010011110000001100100010 .!
b00111001010011100111111001001000 /!
b00000000000011110000000000000000 0!
b10010011111101011001100101111111000000000000111100000000000000000111110110101000011001000000010101100000000000000000001111000110001111101001110101111011011110000000000110000011111111000000000000010010110111001011111111011011111000101110001011000011100011101100100000100001010111000001101010110111001101100111100110100010111001011011110000111001000010010011001001100110001111000101101110011101001000001001110101100111111011001000011100100110110010110111000000100001001110001010010011010011101101111001011100111011 1!
b0001 A!
1B!
b0010 C!
b01111101101010000110010000000101 D!
#20000
b00000000000011110000000000000000 u
0v
b00000000000000000000000000010001 {
0B!
#20500
1v
b10010011111101011001100101111111001110110110100010111010011100111010111111110100111111111100000101100000000000000000001111000110001111101001110101111011011110000000000110000011111111000000000000010010110111001011111111011011111000101110001011000011100011101100100000100001010111000001101010110111001101100111100110100010111001011011110000111001000010010011001001100110001111000101101110011101001000001001110101100111111011001000011100100110110010110111000000100001001110001010010011010011101101111001011100111011 |
b10000000001100011001100001111111 .!
b01111111101101001100011011100010 /!
b01111101101010000110010000000101 0!
b10010011111101011001100101111111001110110110100010111010011100110111110110101000011001000000010101100000000000000000001111000110001111101001110101111011011110000000000110000011111111000000000000010010110111001011111111011011111000101110001011000011100011101100100000100001010111000001101010110111001101100111100110100010111001011011110000111001000010010011001001100110001111000101101110011101001000001001110101100111111011001000011100100110110010110111000000100001001110001010010011010011101101111001011100111011 1!
b0010 A!
1B!
b0011 C!
b01100000000000000000001111000110 D!
#21000
b01111101101010000110010000000101 u
0v
b00000000000000000000000000010010 {
0B!
#21500
1v
b10010011111101011001100101111111001110110110100010111010011100111010111111110100111111111100000111110001000010100101110001100010001111101001110101111011011110000000000110000011111111000000000000010010110111001011111111011011111000101110001011000011100011101100100000100001010111000001101010110111001101100111100110100010111001011011110000111001000010010011001001100110001111000101101110011101001000001001110101100111111011001000011100100110110010110111000000100001001110001010010011010011101101111001011100111011 |
b10101001011100001001101000111110 .!
b01001010011110010010000011110111 /!
b01100000000000000000001111000110 0!
b10010011111101011001100101111111001110110110100010111010011100111010111111110100111111111100000101100000000000000000001111000110001111101001110101111011011110000000000110000011111111000000000000010010110111001011111111011011111000101110001011000011100011101100100000100001010111000001101010110111001101100111100110100010111001011011110000111001000010010011001001100110001111000101101110011101001000001001110101100111111011001000011100100110110010110111000000100001001110001010010011010011101101111001011100111011 1!
b0011 A!
1B!
b0100 C!
b00111110100111010111101101111000 D!
#22000
b01100000000000000000001111000110 u
0v
b00000000000000000000000000010011 {
0B!
#22500
1v
b10010011111101011001100101111111001110110110100010111010011100111010111111110100111111111100000111110001000010100101110001100010000010101000101100111001100101100000000110000011111111000000000000010010110111001011111111011011111000101110001011000011100011101100100000100001010111000001101010110111001101100111100110100010111001011011110000111001000010010011001001100110001111000101101110011101001000001001110101100111111011001000011100100110110010110111000000100001001110001010010011010011101101111001011100111011 |
b11111111001100110111100000011000 .!
b11100000001100110001111100111011 /!
b00111110100111010111101101111000 0!
b10010011111101011001100101111111001110110110100010111010011100111010111111110100111111111100000111110001000010100101110001100010001111101001110101111011011110000000000110000011111111000000000000010010110111001011111111011011111000101110001011000011100011101100100000100001010111000001101010110111001101100111100110100010111001011011110000111001000010010011001001100110001111000101101110011101001000001001110101100111111011001000011100100110110010110111000000100001001110001010010011010011101101111001011100111011 1!
b0100 A!
1B!
b0101 C!
b00000001100000111111110000000000 D!
#23000
b00111110100111010111101101111000 u
0v
b00000000000000000000000000010100 {
0B!
#23500
1v
b10010011111101011001100101111111001110110110100010111010011100111010111111110100111111111100000111110001000010100101110001100010000010101000101100111001100101100111001010101111100000110000101000010010110111001011111111011011111000101110001011000011100011101100100000100001010111000001101010110111001101100111100110100010111001011011110000111001000010010011001001100110001111000101101110011101001000001001110101100111111011001000011100100110110010110111000000100001001110001010010011010011101101111001011100111011 |
b10011011100010001110101000110011 .!
b01100101100000010110010000110011 /!
b00000001100000111111110000000000 0!
b10010011111101011001100101111111001110110110100010111010011100111010111111110100111111111100000111110001000010100101110001100010000010101000101100111001100101100000000110000011111111000000000000010010110111001011111111011011111000101110001011000011100011101100100000100001010111000001101010110111001101100111100110100010111001011011110000111001000010010011001001100110001111000101101110011101001000001001110101100111111011001000011100100110110010110111000000100001001110001010010011010011101101111001011100111011 1!
b0101 A!
1B!
b0110 C!
b00010010110111001011111111011011 D!
#24000
b00000001100000111111110000000000 u
0v
b00000000000000000000000000010101 {
0B!
