Source/preprocessor.sv
`timescale 1ns/10ps

module preprocessor (
    input logic [511:0] data, 
    input logic [63:0] data_len,
    input logic second_block_flag, length512,
    output logic [511:0] preprocessed_block
);

    /* verilator lint_off UNUSEDSIGNAL */
    logic [511:0] masked_data;
    /* verilator lint_on UNUSEDSIGNAL */
    logic [8:0] valid_bits;
    logic [511:0] data_mask;
    logic [511:0] one_bit_mask;

    always_comb begin
        /* verilator lint_off WIDTHTRUNC */
        valid_bits = data_len % 512 ;
        data_mask = 'b0;
        one_bit_mask = 'b0;
        /* verilator lint_off WIDTHTRUNC */
        if (valid_bits == 0 && data_len != 0) begin
            // Last block to be processed is 512 bits. First preprocessed block is the entire data. 
            masked_data = data;
        end else begin
            data_mask = {512{1'b1}} << (512 - valid_bits);
            one_bit_mask = 512'b1 << (511 - valid_bits);
            masked_data = (data & data_mask) | one_bit_mask;
        end
        // Check if this is the first or second processed block.
        if (second_block_flag) begin
            // Processed block is 1024 bits, first preprocessed block has already been hashed. Need to send next 512 block.
            // if the length of the block to be processed is 448, then the 1 has been already placed in the first preprocessed block
            // if the length of the block to be processed is 512, then place the one as the first bit
            preprocessed_block = (length512)? {1'b1, 447'b0, data_len} : {448'b0, data_len} ;
        end else if (valid_bits >= 448 || valid_bits == 0) begin
            // First block of edge case (1024 preprocessed block size)
            preprocessed_block = masked_data;
        end else begin
            // preprocessed block is a single 512 bit block
            preprocessed_block = {masked_data[511:64] , data_len};
        end
    end

endmodule

Testbench/tb_preprocessor.sv
`timescale 1ns/10ps
/* verilator coverage_off */
module tb_preprocessor ();

    localparam DELAY = 10ns;

    logic [63:0] data_len;
    logic second_block_flag, length512;
    logic [511:0] data, preprocessed_block;

    logic [1023:0] golden_output;
    string test_string;
    byte test_bytes[64];

    preprocessor dut (
        .data_len(data_len),
        .second_block_flag(second_block_flag),
        .length512(length512),
        .preprocessed_block(preprocessed_block),
        .data(data)
    );

    task preprocess_data;
        input string str;
    begin
        longint str_len;
        byte str_bytes[128];

        str_len = str.len() * 8;
        golden_output = '0;

        foreach (str[i]) begin
            str_bytes[i] = str[i];
        end

        golden_output = {>>{str_bytes}};

        /* verilator lint_off WIDTHTRUNC */
        golden_output[1023 - str_len] = 1'b1;
        /* verilator lint_on WIDTHTRUNC */

        if(str_len < 448) begin
            golden_output[575:512] = str_len;
        end else begin     
            golden_output[63:0] = str_len;
        end
    end
    endtask

    task initialize_inputs;
    begin
        data_len = '0;
        second_block_flag = 0;
        length512 = 0;
        data = '0;
    end
    endtask

    task set_data;
        input string s;
    begin

        test_bytes = '{default: 8'h00};

        foreach (s[i]) begin
            test_bytes[i] = s[i];
        end

        data = {>>{test_bytes}};
    end
    endtask

    task check_data;
    begin

        /* verilator lint_off UNUSEDSIGNAL */
        logic check_pulse, check_mismatch;
        /* verilator lint_off UNUSEDSIGNAL */
        logic [511:0] block;

        check_pulse = 1'b1;
        check_mismatch = 1'b0;

        block = (second_block_flag)? golden_output[511:0] : golden_output [1023:512];

        if (block == preprocessed_block)
            $display("Test passed. data = %h", block);
        else begin
            $display("Test failed. Expected: %h, Got: %h", block, preprocessed_block);
            check_mismatch = 1'b1;
        end

        #1ns; 
        check_pulse = 1'b0;
    end
    endtask

    initial begin

        initialize_inputs;
        #DELAY;

        // Test 1: Data batch is less than 448 bits 
        // In this case the preprocessed block is 512 bits
        test_string = "hello world";
        set_data(test_string); preprocess_data(test_string);
        data_len = test_string.len() * 8;
        #DELAY;
        check_data;

        // Test 2: Data is exactly 448 bits
        // In this case the preprocessed block is 1024 with the 1 placed in the first 512 block
        test_string = "This string is 448 bits long to test the 448-bit case!  ";
        set_data(test_string); preprocess_data(test_string);
        data_len = test_string.len() * 8;
        #DELAY;
        check_data;
        second_block_flag = 1'b1;
        #DELAY;
        check_data;
        second_block_flag = 1'b0;

        // Test 3: Data is between 448 and 512 bits
        // Similar to the previous case , the preprocessed block is 1024 with the 1 placed in the first 512 block
        test_string = "This string is exactly 62 bytes long to test padding case 2.";
        set_data(test_string); preprocess_data(test_string);
        data_len = test_string.len() * 8;
        #DELAY;
        check_data;
        second_block_flag = 1'b1;
        #DELAY;
        check_data;
        second_block_flag = 1'b0;

        // Test 4: Data is exactly 512 bits
        // In this case the preprocessed block is 1024 with the 1 placed in the second 512 block
        test_string = "This string is 64 bytes a full block forcing a new padding block";
        set_data(test_string); preprocess_data(test_string);
        data_len = test_string.len() * 8;
        length512 = 1'b1;
        #DELAY;
        check_data;
        second_block_flag = 1'b1;
        #DELAY;
        check_data;
        second_block_flag = 1'b0;

        $finish;
    end

    
    initial begin
        void'($system("mkdir -p waves"));
        $dumpfile("waves/tb_preprocessor.vcd");
        $dumpvars(0, tb_preprocessor);
    end

endmodule
/* verilator coverage_on */

waves/tb_preprocessor.vcd
$version Generated by VerilatedVcd $end
$timescale 10ps $end
 $scope module tb_preprocessor $end
  $var real 64 N! DELAY $end
  $var wire 64 # data_len [63:0] $end
  $var wire 1 % second_block_flag $end
  $var wire 1 & length512 $end
  $var wire 512 ' data [511:0] $end
  $var wire 512 k preprocessed_block [511:0] $end
  $var wire 1024 7 golden_output [1023:0] $end
  $scope module check_data__Vstatic__unnamedblk4 $end
   $var wire 1 W check_pulse $end
   $var wire 1 X check_mismatch $end
   $var wire 512 Y block [511:0] $end
  $upscope $end
  $scope module dut $end
   $var wire 512 ' data [511:0] $end
   $var wire 64 # data_len [63:0] $end
   $var wire 1 % second_block_flag $end
   $var wire 1 & length512 $end
   $var wire 512 k preprocessed_block [511:0] $end
   $var wire 512 { masked_data [511:0] $end
   $var wire 9 -! valid_bits [8:0] $end
   $var wire 512 .! data_mask [511:0] $end
   $var wire 512 >! one_bit_mask [511:0] $end
  $upscope $end
  $scope module preprocess_data__Vstatic__unnamedblk1 $end
   $var wire 64 i str_len [63:0] $end
  $upscope $end
 $upscope $end
$enddefinitions $end


#0
b0000000000000000000000000000000000000000000000000000000000000000 #
0%
0&
b00000000000000000000000000000000000000000000000000000000000000000000000000000000000000000000000000000000000000000000000000000000000000000000000000000000000000000000000000000000000000000000000000000000000000000000000000000000000000000000000000000000000000000000000000000000000000000000000000000000000000000000000000000000000000000000000000000000000000000000000000000000000000000000000000000000000000000000000000000000000000000000000000000000000000000000000000000000000000000000000000000000000000000000000000000000 '
b0000000000000000000000000000000000000000000000000000000000000000000000000000000000000000000000000000000000000000000000000000000000000000000000000000000000000000000000000000000000000000000000000000000000000000000000000000000000000000000000000000000000000000000000000000000000000000000000000000000000000000000000000000000000000000000000000000000000000000000000000000000000000000000000000000000000000000000000000000000000000000000000000000000000000000000000000000000000000000000000000000000000000000000000000000000000000000000000000000000000000000000000000000000000000000000000000000000000000000000000000000000000000000000000000000000000000000000000000000000000000000000000000000000000000000000000000000000000000000000000000000000000000000000000000000000000000000000000000000000000000000000000000000000000000000000000000000000000000000000000000000000000000000000000000000000000000000000000000000000000000000000000000000000000000000000000000000000000000000000000000000000000000000000000000000000000000000000000000000000000000000 7
0W
0X
b00000000000000000000000000000000000000000000000000000000000000000000000000000000000000000000000000000000000000000000000000000000000000000000000000000000000000000000000000000000000000000000000000000000000000000000000000000000000000000000000000000000000000000000000000000000000000000000000000000000000000000000000000000000000000000000000000000000000000000000000000000000000000000000000000000000000000000000000000000000000000000000000000000000000000000000000000000000000000000000000000000000000000000000000000000000 Y
b0000000000000000000000000000000000000000000000000000000000000000 i
b00000000000000000000000000000000000000000000000000000000000000000000000000000000000000000000000000000000000000000000000000000000000000000000000000000000000000000000000000000000000000000000000000000000000000000000000000000000000000000000000000000000000000000000000000000000000000000000000000000000000000000000000000000000000000000000000000000000000000000000000000000000000000000000000000000000000000000000000000000000000000000000000000000000000000000000000000000000000000000000000000000000000000000000000000000000 k
b00000000000000000000000000000000000000000000000000000000000000000000000000000000000000000000000000000000000000000000000000000000000000000000000000000000000000000000000000000000000000000000000000000000000000000000000000000000000000000000000000000000000000000000000000000000000000000000000000000000000000000000000000000000000000000000000000000000000000000000000000000000000000000000000000000000000000000000000000000000000000000000000000000000000000000000000000000000000000000000000000000000000000000000000000000000 {
b000000000 -!
b00000000000000000000000000000000000000000000000000000000000000000000000000000000000000000000000000000000000000000000000000000000000000000000000000000000000000000000000000000000000000000000000000000000000000000000000000000000000000000000000000000000000000000000000000000000000000000000000000000000000000000000000000000000000000000000000000000000000000000000000000000000000000000000000000000000000000000000000000000000000000000000000000000000000000000000000000000000000000000000000000000000000000000000000000000000 .!
b00000000000000000000000000000000000000000000000000000000000000000000000000000000000000000000000000000000000000000000000000000000000000000000000000000000000000000000000000000000000000000000000000000000000000000000000000000000000000000000000000000000000000000000000000000000000000000000000000000000000000000000000000000000000000000000000000000000000000000000000000000000000000000000000000000000000000000000000000000000000000000000000000000000000000000000000000000000000000000000000000000000000000000000000000000000 >!
r10 N!
#1000
b0000000000000000000000000000000000000000000000000000000001011000 #
b01101000011001010110110001101100011011110010000001110111011011110111001001101100011001000000000000000000000000000000000000000000000000000000000000000000000000000000000000000000000000000000000000000000000000000000000000000000000000000000000000000000000000000000000000000000000000000000000000000000000000000000000000000000000000000000000000000000000000000000000000000000000000000000000000000000000000000000000000000000000000000000000000000000000000000000000000000000000000000000000000000000000000000000000000000000 '
b0110100001100101011011000110110001101111001000000111011101101111011100100110110001100100100000000000000000000000000000000000000000000000000000000000000000000000000000000000000000000000000000000000000000000000000000000000000000000000000000000000000000000000000000000000000000000000000000000000000000000000000000000000000000000000000000000000000000000000000000000000000000000000000000000000000000000000000000000000000000000000000000000000000000000000000000000000000000000000000000000000000000000000000000000101100000000000000000000000000000000000000000000000000000000000000000000000000000000000000000000000000000000000000000000000000000000000000000000000000000000000000000000000000000000000000000000000000000000000000000000000000000000000000000000000000000000000000000000000000000000000000000000000000000000000000000000000000000000000000000000000000000000000000000000000000000000000000000000000000000000000000000000000000000000000000000000000000000000000000000000000000000000000000000000000000000000000000000000000000000000000 7
b0000000000000000000000000000000000000000000000000000000001011000 i
b01101000011001010110110001101100011011110010000001110111011011110111001001101100011001001000000000000000000000000000000000000000000000000000000000000000000000000000000000000000000000000000000000000000000000000000000000000000000000000000000000000000000000000000000000000000000000000000000000000000000000000000000000000000000000000000000000000000000000000000000000000000000000000000000000000000000000000000000000000000000000000000000000000000000000000000000000000000000000000000000000000000000000000000000001011000 k
b01101000011001010110110001101100011011110010000001110111011011110111001001101100011001001000000000000000000000000000000000000000000000000000000000000000000000000000000000000000000000000000000000000000000000000000000000000000000000000000000000000000000000000000000000000000000000000000000000000000000000000000000000000000000000000000000000000000000000000000000000000000000000000000000000000000000000000000000000000000000000000000000000000000000000000000000000000000000000000000000000000000000000000000000000000000 {
b001011000 -!
b11111111111111111111111111111111111111111111111111111111111111111111111111111111111111110000000000000000000000000000000000000000000000000000000000000000000000000000000000000000000000000000000000000000000000000000000000000000000000000000000000000000000000000000000000000000000000000000000000000000000000000000000000000000000000000000000000000000000000000000000000000000000000000000000000000000000000000000000000000000000000000000000000000000000000000000000000000000000000000000000000000000000000000000000000000000 .!
b00000000000000000000000000000000000000000000000000000000000000000000000000000000000000001000000000000000000000000000000000000000000000000000000000000000000000000000000000000000000000000000000000000000000000000000000000000000000000000000000000000000000000000000000000000000000000000000000000000000000000000000000000000000000000000000000000000000000000000000000000000000000000000000000000000000000000000000000000000000000000000000000000000000000000000000000000000000000000000000000000000000000000000000000000000000 >!
#2000
1W
b01101000011001010110110001101100011011110010000001110111011011110111001001101100011001001000000000000000000000000000000000000000000000000000000000000000000000000000000000000000000000000000000000000000000000000000000000000000000000000000000000000000000000000000000000000000000000000000000000000000000000000000000000000000000000000000000000000000000000000000000000000000000000000000000000000000000000000000000000000000000000000000000000000000000000000000000000000000000000000000000000000000000000000000000001011000 Y
#2100
b0000000000000000000000000000000000000000000000000000000111000000 #
b01010100011010000110100101110011001000000111001101110100011100100110100101101110011001110010000001101001011100110010000000110100001101000011100000100000011000100110100101110100011100110010000001101100011011110110111001100111001000000111010001101111001000000111010001100101011100110111010000100000011101000110100001100101001000000011010000110100001110000010110101100010011010010111010000100000011000110110000101110011011001010010000100100000001000000000000000000000000000000000000000000000000000000000000000000000 '
b0101010001101000011010010111001100100000011100110111010001110010011010010110111001100111001000000110100101110011001000000011010000110100001110000010000001100010011010010111010001110011001000000110110001101111011011100110011100100000011101000110111100100000011101000110010101110011011101000010000001110100011010000110010100100000001101000011010000111000001011010110001001101001011101000010000001100011011000010111001101100101001000010010000000100000100000000000000000000000000000000000000000000000000000000000000000000000000000000000000000000000000000000000000000000000000000000000000000000000000000000000000000000000000000000000000000000000000000000000000000000000000000000000000000000000000000000000000000000000000000000000000000000000000000000000000000000000000000000000000000000000000000000000000000000000000000000000000000000000000000000000000000000000000000000000000000000000000000000000000000000000000000000000000000000000000000000000000000000000000000000000000000000000000000000000000000000000000000000000000111000000 7
0W
b0000000000000000000000000000000000000000000000000000000111000000 i
b01010100011010000110100101110011001000000111001101110100011100100110100101101110011001110010000001101001011100110010000000110100001101000011100000100000011000100110100101110100011100110010000001101100011011110110111001100111001000000111010001101111001000000111010001100101011100110111010000100000011101000110100001100101001000000011010000110100001110000010110101100010011010010111010000100000011000110110000101110011011001010010000100100000001000001000000000000000000000000000000000000000000000000000000000000000 k
b01010100011010000110100101110011001000000111001101110100011100100110100101101110011001110010000001101001011100110010000000110100001101000011100000100000011000100110100101110100011100110010000001101100011011110110111001100111001000000111010001101111001000000111010001100101011100110111010000100000011101000110100001100101001000000011010000110100001110000010110101100010011010010111010000100000011000110110000101110011011001010010000100100000001000001000000000000000000000000000000000000000000000000000000000000000 {
b111000000 -!
b11111111111111111111111111111111111111111111111111111111111111111111111111111111111111111111111111111111111111111111111111111111111111111111111111111111111111111111111111111111111111111111111111111111111111111111111111111111111111111111111111111111111111111111111111111111111111111111111111111111111111111111111111111111111111111111111111111111111111111111111111111111111111111111111111111111111111111111111111111111111111111111111111111111111111110000000000000000000000000000000000000000000000000000000000000000 .!
b00000000000000000000000000000000000000000000000000000000000000000000000000000000000000000000000000000000000000000000000000000000000000000000000000000000000000000000000000000000000000000000000000000000000000000000000000000000000000000000000000000000000000000000000000000000000000000000000000000000000000000000000000000000000000000000000000000000000000000000000000000000000000000000000000000000000000000000000000000000000000000000000000000000000000001000000000000000000000000000000000000000000000000000000000000000 >!
#3100
1W
b01010100011010000110100101110011001000000111001101110100011100100110100101101110011001110010000001101001011100110010000000110100001101000011100000100000011000100110100101110100011100110010000001101100011011110110111001100111001000000111010001101111001000000111010001100101011100110111010000100000011101000110100001100101001000000011010000110100001110000010110101100010011010010111010000100000011000110110000101110011011001010010000100100000001000001000000000000000000000000000000000000000000000000000000000000000 Y
#3200
1%
0W
b00000000000000000000000000000000000000000000000000000000000000000000000000000000000000000000000000000000000000000000000000000000000000000000000000000000000000000000000000000000000000000000000000000000000000000000000000000000000000000000000000000000000000000000000000000000000000000000000000000000000000000000000000000000000000000000000000000000000000000000000000000000000000000000000000000000000000000000000000000000000000000000000000000000000000000000000000000000000000000000000000000000000000000000000111000000 k
#4200
1W
b00000000000000000000000000000000000000000000000000000000000000000000000000000000000000000000000000000000000000000000000000000000000000000000000000000000000000000000000000000000000000000000000000000000000000000000000000000000000000000000000000000000000000000000000000000000000000000000000000000000000000000000000000000000000000000000000000000000000000000000000000000000000000000000000000000000000000000000000000000000000000000000000000000000000000000000000000000000000000000000000000000000000000000000000111000000 Y
#4300
b0000000000000000000000000000000000000000000000000000000111100000 #
0%
b01010100011010000110100101110011001000000111001101110100011100100110100101101110011001110010000001101001011100110010000001100101011110000110000101100011011101000110110001111001001000000011011000110010001000000110001001111001011101000110010101110011001000000110110001101111011011100110011100100000011101000110111100100000011101000110010101110011011101000010000001110000011000010110010001100100011010010110111001100111001000000110001101100001011100110110010100100000001100100010111000000000000000000000000000000000 '
b0101010001101000011010010111001100100000011100110111010001110010011010010110111001100111001000000110100101110011001000000110010101111000011000010110001101110100011011000111100100100000001101100011001000100000011000100111100101110100011001010111001100100000011011000110111101101110011001110010000001110100011011110010000001110100011001010111001101110100001000000111000001100001011001000110010001101001011011100110011100100000011000110110000101110011011001010010000000110010001011101000000000000000000000000000000000000000000000000000000000000000000000000000000000000000000000000000000000000000000000000000000000000000000000000000000000000000000000000000000000000000000000000000000000000000000000000000000000000000000000000000000000000000000000000000000000000000000000000000000000000000000000000000000000000000000000000000000000000000000000000000000000000000000000000000000000000000000000000000000000000000000000000000000000000000000000000000000000000000000000000000000000000000000000000000000000000000000000000000000111100000 7
0W
b0000000000000000000000000000000000000000000000000000000111100000 i
b01010100011010000110100101110011001000000111001101110100011100100110100101101110011001110010000001101001011100110010000001100101011110000110000101100011011101000110110001111001001000000011011000110010001000000110001001111001011101000110010101110011001000000110110001101111011011100110011100100000011101000110111100100000011101000110010101110011011101000010000001110000011000010110010001100100011010010110111001100111001000000110001101100001011100110110010100100000001100100010111010000000000000000000000000000000 k
b01010100011010000110100101110011001000000111001101110100011100100110100101101110011001110010000001101001011100110010000001100101011110000110000101100011011101000110110001111001001000000011011000110010001000000110001001111001011101000110010101110011001000000110110001101111011011100110011100100000011101000110111100100000011101000110010101110011011101000010000001110000011000010110010001100100011010010110111001100111001000000110001101100001011100110110010100100000001100100010111010000000000000000000000000000000 {
b111100000 -!
b11111111111111111111111111111111111111111111111111111111111111111111111111111111111111111111111111111111111111111111111111111111111111111111111111111111111111111111111111111111111111111111111111111111111111111111111111111111111111111111111111111111111111111111111111111111111111111111111111111111111111111111111111111111111111111111111111111111111111111111111111111111111111111111111111111111111111111111111111111111111111111111111111111111111111111111111111111111111111111111111100000000000000000000000000000000 .!
b00000000000000000000000000000000000000000000000000000000000000000000000000000000000000000000000000000000000000000000000000000000000000000000000000000000000000000000000000000000000000000000000000000000000000000000000000000000000000000000000000000000000000000000000000000000000000000000000000000000000000000000000000000000000000000000000000000000000000000000000000000000000000000000000000000000000000000000000000000000000000000000000000000000000000000000000000000000000000000000000010000000000000000000000000000000 >!
#5300
1W
b01010100011010000110100101110011001000000111001101110100011100100110100101101110011001110010000001101001011100110010000001100101011110000110000101100011011101000110110001111001001000000011011000110010001000000110001001111001011101000110010101110011001000000110110001101111011011100110011100100000011101000110111100100000011101000110010101110011011101000010000001110000011000010110010001100100011010010110111001100111001000000110001101100001011100110110010100100000001100100010111010000000000000000000000000000000 Y
#5400
1%
0W
b00000000000000000000000000000000000000000000000000000000000000000000000000000000000000000000000000000000000000000000000000000000000000000000000000000000000000000000000000000000000000000000000000000000000000000000000000000000000000000000000000000000000000000000000000000000000000000000000000000000000000000000000000000000000000000000000000000000000000000000000000000000000000000000000000000000000000000000000000000000000000000000000000000000000000000000000000000000000000000000000000000000000000000000000111100000 k
#6400
1W
b00000000000000000000000000000000000000000000000000000000000000000000000000000000000000000000000000000000000000000000000000000000000000000000000000000000000000000000000000000000000000000000000000000000000000000000000000000000000000000000000000000000000000000000000000000000000000000000000000000000000000000000000000000000000000000000000000000000000000000000000000000000000000000000000000000000000000000000000000000000000000000000000000000000000000000000000000000000000000000000000000000000000000000000000111100000 Y
#6500
b0000000000000000000000000000000000000000000000000000001000000000 #
0%
1&
b01010100011010000110100101110011001000000111001101110100011100100110100101101110011001110010000001101001011100110010000000110110001101000010000001100010011110010111010001100101011100110010000001100001001000000110011001110101011011000110110000100000011000100110110001101111011000110110101100100000011001100110111101110010011000110110100101101110011001110010000001100001001000000110111001100101011101110010000001110000011000010110010001100100011010010110111001100111001000000110001001101100011011110110001101101011 '
b0101010001101000011010010111001100100000011100110111010001110010011010010110111001100111001000000110100101110011001000000011011000110100001000000110001001111001011101000110010101110011001000000110000100100000011001100111010101101100011011000010000001100010011011000110111101100011011010110010000001100110011011110111001001100011011010010110111001100111001000000110000100100000011011100110010101110111001000000111000001100001011001000110010001101001011011100110011100100000011000100110110001101111011000110110101110000000000000000000000000000000000000000000000000000000000000000000000000000000000000000000000000000000000000000000000000000000000000000000000000000000000000000000000000000000000000000000000000000000000000000000000000000000000000000000000000000000000000000000000000000000000000000000000000000000000000000000000000000000000000000000000000000000000000000000000000000000000000000000000000000000000000000000000000000000000000000000000000000000000000000000000000000000000000000000000000000000000000000000001000000000 7
0W
b0000000000000000000000000000000000000000000000000000001000000000 i
b01010100011010000110100101110011001000000111001101110100011100100110100101101110011001110010000001101001011100110010000000110110001101000010000001100010011110010111010001100101011100110010000001100001001000000110011001110101011011000110110000100000011000100110110001101111011000110110101100100000011001100110111101110010011000110110100101101110011001110010000001100001001000000110111001100101011101110010000001110000011000010110010001100100011010010110111001100111001000000110001001101100011011110110001101101011 k
b01010100011010000110100101110011001000000111001101110100011100100110100101101110011001110010000001101001011100110010000000110110001101000010000001100010011110010111010001100101011100110010000001100001001000000110011001110101011011000110110000100000011000100110110001101111011000110110101100100000011001100110111101110010011000110110100101101110011001110010000001100001001000000110111001100101011101110010000001110000011000010110010001100100011010010110111001100111001000000110001001101100011011110110001101101011 {
b000000000 -!
b00000000000000000000000000000000000000000000000000000000000000000000000000000000000000000000000000000000000000000000000000000000000000000000000000000000000000000000000000000000000000000000000000000000000000000000000000000000000000000000000000000000000000000000000000000000000000000000000000000000000000000000000000000000000000000000000000000000000000000000000000000000000000000000000000000000000000000000000000000000000000000000000000000000000000000000000000000000000000000000000000000000000000000000000000000000 .!
b00000000000000000000000000000000000000000000000000000000000000000000000000000000000000000000000000000000000000000000000000000000000000000000000000000000000000000000000000000000000000000000000000000000000000000000000000000000000000000000000000000000000000000000000000000000000000000000000000000000000000000000000000000000000000000000000000000000000000000000000000000000000000000000000000000000000000000000000000000000000000000000000000000000000000000000000000000000000000000000000000000000000000000000000000000000 >!
#7500
1W
b01010100011010000110100101110011001000000111001101110100011100100110100101101110011001110010000001101001011100110010000000110110001101000010000001100010011110010111010001100101011100110010000001100001001000000110011001110101011011000110110000100000011000100110110001101111011000110110101100100000011001100110111101110010011000110110100101101110011001110010000001100001001000000110111001100101011101110010000001110000011000010110010001100100011010010110111001100111001000000110001001101100011011110110001101101011 Y
#7600
1%
0W
b10000000000000000000000000000000000000000000000000000000000000000000000000000000000000000000000000000000000000000000000000000000000000000000000000000000000000000000000000000000000000000000000000000000000000000000000000000000000000000000000000000000000000000000000000000000000000000000000000000000000000000000000000000000000000000000000000000000000000000000000000000000000000000000000000000000000000000000000000000000000000000000000000000000000000000000000000000000000000000000000000000000000000000000001000000000 k
#8600
1W
b10000000000000000000000000000000000000000000000000000000000000000000000000000000000000000000000000000000000000000000000000000000000000000000000000000000000000000000000000000000000000000000000000000000000000000000000000000000000000000000000000000000000000000000000000000000000000000000000000000000000000000000000000000000000000000000000000000000000000000000000000000000000000000000000000000000000000000000000000000000000000000000000000000000000000000000000000000000000000000000000000000000000000000000001000000000 Y
#8700
0%
0W
b01010100011010000110100101110011001000000111001101110100011100100110100101101110011001110010000001101001011100110010000000110110001101000010000001100010011110010111010001100101011100110010000001100001001000000110011001110101011011000110110000100000011000100110110001101111011000110110101100100000011001100110111101110010011000110110100101101110011001110010000001100001001000000110111001100101011101110010000001110000011000010110010001100100011010010110111001100111001000000110001001101100011011110110001101101011 k
